datasette_column_inspect/__init__.py
datasette_column_inspect/templates/table.html
datasette_column_inspect-0.2a0.dist-info/LICENSE
datasette_column_inspect-0.2a0.dist-info/METADATA
datasette_column_inspect-0.2a0.dist-info/WHEEL
datasette_column_inspect-0.2a0.dist-info/entry_points.txt
datasette_column_inspect-0.2a0.dist-info/top_level.txt
datasette_column_inspect-0.2a0.dist-info/RECORD
