Metadata-Version: 2.1
Name: datasette-column-inspect
Version: 0.2a0
Summary: Experimental Datasette plugin for inspecting columns
Home-page: https://github.com/simonw/datasette-column-inspect
Author: Simon Willison
License: Apache License, Version 2.0
Platform: UNKNOWN
Requires-Dist: datasette
Provides-Extra: test
Requires-Dist: pytest ; extra == 'test'
Requires-Dist: pytest-asyncio ; extra == 'test'
Requires-Dist: httpx ; extra == 'test'
Requires-Dist: sqlite-utils ; extra == 'test'
